guojiqe_sdk/__init__.py
guojiqe_sdk/backend.py
guojiqe_sdk/base.py
guojiqe_sdk/client.py
guojiqe_sdk/device_types.py
guojiqe_sdk/job.py
guojiqe_sdk/noise_model.py
guojiqe_sdk/runtime_service.py
tests/__init__.py
guojiqe_sdk-0.1.0.dist-info/METADATA
guojiqe_sdk-0.1.0.dist-info/WHEEL
guojiqe_sdk-0.1.0.dist-info/top_level.txt
guojiqe_sdk-0.1.0.dist-info/RECORD
