Metadata-Version: 2.2
Name: guojiqe-sdk
Version: 0.1.0
Summary: A Python SDK for interacting with Guoji Quantum's quantum computing services.
Home-page: https://github.com/yourusername/my-sdk
Author: CETC Guoji Quantum
Author-email: your.email@example.com
Classifier: Development Status :: 3 - Alpha
Classifier: Intended Audience :: Developers
Classifier: License :: OSI Approved :: MIT License
Classifier: Operating System :: OS Independent
Classifier: Programming Language :: Python :: 3.9
Classifier: Programming Language :: Python :: 3.10
Requires-Python: >=3.9
Requires-Dist: qiskit>=2.0.0
Dynamic: author
Dynamic: author-email
Dynamic: classifier
Dynamic: description-content-type
Dynamic: home-page
Dynamic: requires-dist
Dynamic: requires-python
Dynamic: summary
